har2locust/__init__.py
har2locust/__main__.py
har2locust/_version.py
har2locust/argument_parser.py
har2locust/locust.jinja2
har2locust/plugin.py
har2locust/default_plugins/1_resourcefilter.py
har2locust/default_plugins/2_methodignore.py
har2locust/default_plugins/default_headers.py
har2locust/default_plugins/headerignore.py
har2locust/default_plugins/rest.py
har2locust/default_plugins/ruff.py
har2locust/default_plugins/urlignore.py
har2locust/extra_plugins/plugin_example.py
har2locust-0.9.3.dist-info/LICENSE
har2locust-0.9.3.dist-info/METADATA
har2locust-0.9.3.dist-info/WHEEL
har2locust-0.9.3.dist-info/entry_points.txt
har2locust-0.9.3.dist-info/top_level.txt
har2locust-0.9.3.dist-info/RECORD
